{"questions":[{"question":"1) Ao circular nesta via e perante este sinal, fico a saber que:","optionA":"A 500 metros, vou ter informação sobre onde se encontra um posto de abastecimento de combustível.","optionB":"Se encontra a 500 metros um posto de abastecimento de combustível com GPL.","optionC":"Se encontra a 500 metros um posto de abastecimento de combustível.","correct":"C","imageHash":"2pmwyr8e.jpg","imageName":"2pmwyr8e.jpg","topicName":"Sinais de indicação"},{"question":"2) Este sinal é de:","optionA":"Informação.","optionB":"Cedência de passagem.","optionC":"Selecção de vias.","correct":"B","imageHash":"kpabrz8g.jpg","imageName":"kpabrz8g.jpg","topicName":"Sinais de prescrição específica, sinais de cedência de passagem"},{"question":"3) A condução defensiva tem como principal objectivo:","optionA":"Cumprir apenas o Código da Estrada.","optionB":"A segurança rodoviária.","optionC":"Ser sempre o primeiro a avançar.","correct":"B","imageHash":"q89vq2d4.jpg","imageName":"q89vq2d4.jpg","topicName":"Iluminação, passageiros e carga, condução defensiva e peões"},{"question":"4) O documento de identificação do veículo pode ser apreendido pelas autoridades de fiscalização?","optionA":"Não.","optionB":"Sim, se o condutor não for o proprietário.","optionC":"Sim, se estiver em mau estado de conservação, tornando ilegível qualquer informação.","correct":"C","imageHash":"6d5okzpv.jpg","imageName":"6d5okzpv.jpg","topicName":"Títulos de condução, obtenção, revalidação, responsabilidade civil e criminal, contra-ordenações, cassação"},{"question":"5) Neste local a faixa de rodagem:","optionA":"Tem duas vias de trânsito.","optionB":"Tem três sentidos de trânsito.","optionC":"Tem três vias de trânsito.","correct":"C","imageHash":"ydexvnpz.jpg","imageName":"ydexvnpz.jpg","topicName":"Circulação, segurança e veículos em missão urgente de socorro"},{"question":"6) Perante o sinal vertical devo saber que:","optionA":"O trânsito apenas se faz num só sentido.","optionB":"Aproxima-se uma curva perigosa à esquerda.","optionC":"Tenho prioridade de passagem no próximo entroncamento ou cruzamento.","correct":"B","imageHash":"r84qaydo.jpg","imageName":"r84qaydo.jpg","topicName":"Sinais de prescrição específica, sinais de cedência de passagem"},{"question":"7) Um condutor deve saber que o carácter provisório da carta de condução obriga sempre a:","optionA":"Realizar novo exame para obter a carta de condução definitiva.","optionB":"Um regime contra-ordenacional mais penalizante.","optionC":"Ter que aguardar o fim do período probatório para obter o título definitivo independentemente das infracções que pratique.","correct":"B","imageHash":"a8vneldk.jpg","imageName":"a8vneldk.jpg","topicName":"Títulos de condução, obtenção, revalidação, responsabilidade civil e criminal, contra-ordenações, cassação"},{"question":"8) A sanção de inibição de conduzir, pela prática de uma contra-ordenação grave, tem a duração máxima de:","optionA":"Um mês.","optionB":"Dois meses.","optionC":"Um ano.","correct":"C","imageHash":"j8ggjj8w.jpg","imageName":"j8ggjj8w.jpg","topicName":"Títulos de condução, obtenção, revalidação, responsabilidade civil e criminal, contra-ordenações, cassação"},{"question":"9) Ao circular numa auto-estrada o condutor de motociclo deve:","optionA":"Utilizar mudanças altas (5ª e 6ª), reduzir substancialmente a velocidade e conduzir encostado à guia direita.","optionB":"Aumentar a distância de segurança do veículo da frente.","optionC":"Utilizar mudanças altas (5ª e 6ª) reduzindo a distância de segurança, uma vez que a visibilidade aumenta significativamente.","correct":"B","imageHash":"a8vnbydk.jpg","imageName":"a8vnbydk.jpg","topicName":"Classificação das vias"},{"question":"10) Nesta situação devo:","optionA":"Utilizar o motor como auxiliar do travão e moderar a velocidade.","optionB":"Parar, porque as condições atmosféricas não são favoráveis a uma condução segura.","optionC":"Utilizar o travão de serviço e nunca o motor como auxiliar, porque a via não é inclinada.","correct":"A","imageHash":"j8lgrkd7.jpg","imageName":"j8lgrkd7.jpg","topicName":"Vias de trânsito, condições ambientais adversas"},{"question":"11) Como devo proceder para descrever a curva em segurança?","optionA":"Circular à direita da guia.","optionB":"Reduzir a velocidade e aumentar as rotações do motor.","optionC":"Adaptar a velocidade às características da curva.","optionD":"Circular junto ao eixo da faixa de rodagem.","correct":"C","imageHash":"o8xmjqdg.jpg","imageName":"o8xmjqdg.jpg","topicName":"Visibilidade relativamente aos outros utentes da via"},{"question":"12) Este sinal indica-me que o desvio que vou encontrar a 250 metros aplica- se:","optionA":"A todos os automóveis ligeiros.","optionB":"Aos veículos pesados com mais de 3,5 toneladas.","optionC":"Aos veículos com altura superior a 3,5 metros.","optionD":"Aos veículos de mercadorias com mais de 12 toneladas.","correct":"C","imageHash":"qpyavjpg.jpg","imageName":"qpyavjpg.jpg","topicName":"Sinais de proibição"},{"question":"13) Regra geral, onde se encontra colocado o interruptor de emergência dos motociclos?","optionA":"Do lado esquerdo do guiador.","optionB":"Do lado direito do guiador.","optionC":"Indistintamente do lado esquerdo ou direito do guiador.","optionD":"No mesmo local da chave de ignição.","correct":"B","imageHash":"ldrgkzpm.jpg","imageName":"ldrgkzpm.jpg","topicName":"Constituintes do veículo"},{"question":"14) A que distância devo circular da berma?","optionA":"A uma distância nunca inferior a 5 metros.","optionB":"A uma distância suficiente que permita evitar acidentes.","optionC":"A uma distância nunca superior a 5 metros.","optionD":"O mais afastado possível.","correct":"B","imageHash":"6d5ax48v.jpg","imageName":"6d5ax48v.jpg","topicName":"Visibilidade relativamente aos outros utentes da via"},{"question":"15) O estado de limpeza dos faróis pode influenciar a eficácia das luzes.","optionA":"Certo.","optionB":"Errado.","correct":"A","imageHash":"bdo2y683.jpg","imageName":"bdo2y683.jpg","topicName":"Classificação, constituintes, inspecções, pesos e dimensões, protecção de ambiente, equipamentos de segurança, acidente"},{"question":"16) Nesta situação, devo ultrapassar o condutor do velocípede.","optionA":"Certo.","optionB":"Errado.","correct":"B","imageHash":"2pm2ez8e.jpg","imageName":"2pm2ez8e.jpg","topicName":"Ultrapassagem"},{"question":"17) Os condutores de veículos que seguem em missão urgente de socorro são obrigados a parar junto à linha de paragem “STOP” marcada no pavimento, acompanhada pela sinalização vertical?","optionA":"Sim, são obrigados a suspender a marcha.","optionB":"Não, em circunstância alguma.","correct":"A","imageHash":"z8z5aj8n.jpg","imageName":"z8z5aj8n.jpg","topicName":"Circulação, segurança e veículos em missão urgente de socorro"},{"question":"18) Perante a sinalização vertical devo saber que é proibida a circulação de veículos com:","optionA":"Altura superior a 2 metros.","optionB":"Largura superior a 2 metros.","correct":"B","imageHash":"vd7mzzdg.jpg","imageName":"vd7mzzdg.jpg","topicName":"Sinais de proibição"},{"question":"19) Neste local é proibida a ultrapassagem.","optionA":"Certo.","optionB":"Errado.","correct":"A","imageHash":"r84rxbpo.jpg","imageName":"r84rxbpo.jpg","topicName":"Ultrapassagem"},{"question":"20) Se pretender seguir em frente, estou correctamente posicionado nesta via de trânsito?","optionA":"Sim, estou correctamente posicionado.","optionB":"Não, devo passar para a via de trânsito mais à esquerda.","correct":"A","imageHash":"j8l9lz87.jpg","imageName":"j8l9lz87.jpg","topicName":"Sinalização luminosa, marcas no pavimento e outra sinalização"},{"question":"21) Este veículo pesado pode ter 4,2 m de altura?","optionA":"Sim.","optionB":"Não.","correct":"B","imageHash":"6d54448v.jpg","imageName":"6d54448v.jpg","topicName":"Classificação, constituintes, inspecções, pesos e dimensões, protecção de ambiente, equipamentos de segurança, acidente"},{"question":"22) Este sinal indica perigo temporário de projecção de gravilha devido a obras na via pública.","optionA":"Certo.","optionB":"Errado.","correct":"A","imageHash":"o8x225pg.jpg","imageName":"o8x225pg.jpg","topicName":"Sinais de perigo"},{"question":"23) Encontro-me correctamente posicionado na via para:","optionA":"Mudar de direcção para a esquerda.","optionB":"Mudar de direcção para a direita.","correct":"A","imageHash":"3866ga8k.jpg","imageName":"3866ga8k.jpg","topicName":"Outras manobras"},{"question":"24) Regra geral, devo ceder a passagem aos veículos que assinalem que circulam em serviço de urgência?","optionA":"Não.","optionB":"Sim.","correct":"B","imageHash":"r84rzgpo.jpg","imageName":"r84rzgpo.jpg","topicName":"Circulação, segurança e veículos em missão urgente de socorro"},{"question":"25) Pretendo mudar de direcção à esquerda. Devo:","optionA":"Avançar.","optionB":"Ceder a passagem à ambulância.","correct":"B","imageHash":"r84rygpo.jpg","imageName":"r84rygpo.jpg","topicName":"Cedência de passagem"},{"question":"26) Nesta situação devo:","optionA":"Avançar.","optionB":"Ceder a passagem.","correct":"B","imageHash":"3866bv8k.jpg","imageName":"3866bv8k.jpg","topicName":"Paragem, estacionamento e cruzamento de veículos"},{"question":"27) O sinal de indicação está colocado no local exacto da escapatória?","optionA":"Sim.","optionB":"Não.","correct":"B","imageHash":"o8x2jrpg.jpg","imageName":"o8x2jrpg.jpg","topicName":"Sinais de indicação"},{"question":"28) O condutor de um motociclo pode conduzir com uma das mãos fora do guiador?","optionA":"Sim, pode.","optionB":"Não excepto para assinalar qualquer manobra.","correct":"B","imageHash":"adq4om8j.jpg","imageName":"adq4om8j.jpg","topicName":"Visibilidade relativamente aos outros utentes da via"},{"question":"29) Em determinados motociclos a compressão dos amortecedores pode ser regulada?","optionA":"Sim.","optionB":"Não.","correct":"A","imageHash":"kpawlk8g.jpg","imageName":"kpawlk8g.jpg","topicName":"Constituintes do veículo"},{"question":"30) O condutor de um autocarro de passageiros é considerado sob influência do álcool desde que apresente uma taxa de álcool por litro de sangue igual ou superior a:","optionA":"0,5 g/l de sangue.","optionB":"0,3 g/l de sangue.","optionC":"0,2 g/l de sangue.","correct":"C","imageHash":"kpar2mdg.jpg","imageName":"kpar2mdg.jpg","topicName":"Estado físico do condutor, alcool, drogas e medicamentos, sinais de obrigação"},{"question":"31) Os pneus dos automóveis ligeiros devem apresentar um relevo de, pelo menos:","optionA":"1 mm.","optionB":"1,5 mm.","optionC":"1,6 mm.","correct":"C","imageHash":"z8kblm85.jpg","imageName":"z8kblm85.jpg","topicName":"Classificação, constituintes, inspecções, pesos e dimensões, protecção de ambiente, equipamentos de segurança, acidente"},{"question":"32) Conduzo um automóvel ligeiro de mercadorias sem reboque. Após o sinal vertical, não posso circular a uma velocidade superior a:","optionA":"70 km/h.","optionB":"90 km/h.","optionC":"80 km/h.","correct":"C","imageHash":"5dwrnzpg.jpg","imageName":"5dwrnzpg.jpg","topicName":"Velocidade"},{"question":"33) O sinal avisa-me que a minha velocidade deve ser especialmente adaptada:","optionA":"Às condições de visibilidade do local.","optionB":"Às condições de aderência da faixa de rodagem.","optionC":"À inclinação da via.","correct":"B","imageHash":"6d5g4q8v.jpg","imageName":"6d5g4q8v.jpg","topicName":"Vias de trânsito, condições ambientais adversas"},{"question":"34) Num motociclo, a distância de travagem pode variar devido:","optionA":"Ao estado da carroçaria do veículo.","optionB":"Ao estado dos pneumáticos.","optionC":"À potência do motor do veículo.","correct":"B","imageHash":"j8gwwzdw.jpg","imageName":"j8gwwzdw.jpg","topicName":"Constituintes do veículo"},{"question":"35) Nesta situação devo:","optionA":"Buzinar com insistência para advertir o condutor que não pode realizar aquela manobra.","optionB":"Reduzir a velocidade e circular com especial precaução.","optionC":"Acelerar pois tenho o direito de passar primeiro.","correct":"B","imageHash":"kpb4rad9.jpg","imageName":"kpb4rad9.jpg","topicName":"Velocidade"},{"question":"36) O sinal vertical, não proíbe a ultrapassagem aos condutores de:","optionA":"Automóveis pesados de passageiros.","optionB":"Automóveis pesados de mercadorias.","optionC":"Automóveis ligeiros de mercadorias.","correct":"C","imageHash":"kpamvmpg.jpg","imageName":"kpamvmpg.jpg","topicName":"Ultrapassagem"},{"question":"37) Como devo proceder na presença deste sinal vertical?","optionA":"Circular à velocidade que me é permitida naquela via, mas assinalar a presença do meu veículo.","optionB":"Buzinar para assinalar a minha presença.","optionC":"Circular com especial cuidado e prudência.","correct":"C","imageHash":"qpy5zj8g.jpg","imageName":"qpy5zj8g.jpg","topicName":"Sinais de perigo"},{"question":"38) Perante o comportamento do peão, como devo proceder?","optionA":"Reduzir a velocidade e se necessário parar.","optionB":"Utilizar os sinais sonoros e parar.","optionC":"Contornar o peão, utilizando os sinais sonoros.","correct":"A","imageHash":"2pmnr68e.jpg","imageName":"2pmnr68e.jpg","topicName":"Iluminação, passageiros e carga, condução defensiva e peões"},{"question":"39) Dentro das localidades é proibido estacionar:","optionA":"Nos locais destinados a esse fim.","optionB":"A mais de 10 metros das passagens assinaladas para a travessia de peões.","optionC":"De modo a provocar embaraço para os restantes utentes.","correct":"C","imageHash":"j8gn73dw.jpg","imageName":"j8gn73dw.jpg","topicName":"Paragem, estacionamento e cruzamento de veículos"},{"question":"40) O condutor de um motociclo, deve saber que:","optionA":"É proibido circular por cima de qualquer marca rodoviária.","optionB":"Deve evitar a travagem em cima de marcas rodoviárias.","optionC":"Deve inclinar o motociclo, ao passar em cima de marcas rodoviárias.","correct":"B","imageHash":"6d5vrz8v.jpg","imageName":"6d5vrz8v.jpg","topicName":"Classificação das vias"},{"question":"41) Qual deve ser o comportamento do veículo que está a ser ultrapassado?","optionA":"Parar.","optionB":"Manter a velocidade.","optionC":"Diminuir a velocidade.","correct":"B","imageHash":"qp3m5784.jpg","imageName":"qp3m5784.jpg","topicName":"Ultrapassagem"},{"question":"42) Os médios devem projectar-se no solo:","optionA":"E no mínimo, iluminá-lo a 100 metros.","optionB":"E iluminá-lo eficazmente numa distância de 30 metros.","optionC":"E iluminá-lo eficazmente numa distância de 50 metros.","correct":"B","imageHash":"adq5kqdj.jpg","imageName":"adq5kqdj.jpg","topicName":"Iluminação, passageiros e carga, condução defensiva e peões"},{"question":"43) O uso pelo condutor do colete retro-reflector, é obrigatório:","optionA":"Sempre que o condutor proceda à colocação do sinal de pré-sinalização de perigo.","optionB":"Depois do condutor colocar o sinal de pré-sinalização de perigo.","optionC":"Em caso de avaria ou acidente, salvo se o veículo se encontrar imobilizado na faixa de rodagem.","correct":"A","imageHash":"z8kemm85.jpg","imageName":"z8kemm85.jpg","topicName":"Classificação, constituintes, inspecções, pesos e dimensões, protecção de ambiente, equipamentos de segurança, acidente"},{"question":"44) A que velocidade devo circular neste local?","optionA":"A uma velocidade não superior a 60 Km/h.","optionB":"Em marcha lenta ainda que cause embaraço injustificado aos restantes utentes da via.","optionC":"Estou obrigado a circular a uma velocidade especialmente moderada e manter-me atento.","correct":"C","imageHash":"5pn4mnde.jpg","imageName":"5pn4mnde.jpg","topicName":"Velocidade"},{"question":"45) Um capacete de protecção com um bom sistema de ventilação:","optionA":"Evita o embaciamento da viseira.","optionB":"Deve ser utilizado, preferencialmente, no verão.","optionC":"Evita a renovação do ar dentro do capacete.","correct":"A","imageHash":"q89xar84.jpg","imageName":"q89xar84.jpg","topicName":"Equipamento de Protecção"},{"question":"46) Tendo-me enganado no caminho pretendido, como devo proceder para passar a circular em sentido oposto àquele em que sigo?","optionA":"Invertendo o sentido de marcha no local em que me encontro.","optionB":"Seguindo até à rotunda e optando aí pela direcção desejada.","optionC":"Fazendo marcha atrás pela berma e com as luzes de perigo ligadas.","correct":"B","imageHash":"q89xyr84.jpg","imageName":"q89xyr84.jpg","topicName":"Outras manobras"},{"question":"47) O sinal indica:","optionA":"Fim do limite de velocidade imposto por sinalização.","optionB":"Início de uma zona com um limite máximo de velocidade.","optionC":"Fim de uma zona com um limite mínimo de velocidade.","correct":"A","imageHash":"5dwyvz8g.jpg","imageName":"5dwyvz8g.jpg","topicName":"Sinais de prescrição específica, sinais de cedência de passagem"},{"question":"48) As luvas a utilizar pelos condutores de motociclos têm como finalidade:","optionA":"Garantir somente a protecção das mãos em caso de acidente.","optionB":"Garantir a protecção das mãos durante a condução e em caso de acidente.","optionC":"Garantir somente a temperatura adequada das mãos.","correct":"B","imageHash":"5pn469de.jpg","imageName":"5pn469de.jpg","topicName":"Equipamento de Protecção"},{"question":"49) Na paragem de um motociclo, a força de travagem deve ser:","optionA":"Maior na roda de trás.","optionB":"Maior na roda da frente.","optionC":"Igual nas duas rodas.","correct":"B","imageHash":"ap2mned2.jpg","imageName":"ap2mned2.jpg","topicName":"Visibilidade relativamente aos outros utentes da via"},{"question":"50) Devo saber que as marcas rodoviárias do eixo da faixa de rodagem mais próximas de mim, designam-se por:","optionA":"Linha descontínua e seta de selecção.","optionB":"Linha descontínua e seta orientadora do sentido de trânsito.","optionC":"Linha descontínua de aviso intercalada com seta de desvio.","correct":"C","imageHash":"6d5no4dv.jpg","imageName":"6d5no4dv.jpg","topicName":"Sinalização luminosa, marcas no pavimento e outra sinalização"},{"question":"51) O sinal circular de fundo azul indica-me a velocidade:","optionA":"Máxima recomendada.","optionB":"Mínima obrigatória.","optionC":"Máxima permitida.","correct":"B","imageHash":"38624vpk.jpg","imageName":"38624vpk.jpg","topicName":"Estado físico do condutor, alcool, drogas e medicamentos, sinais de obrigação"},{"question":"52) A marca rodoviária proíbe a paragem?","optionA":"Não, se a paragem se destinar à entrada ou saída de passageiros.","optionB":"Não, se a paragem se destinar a cargas e descargas.","optionC":"Não, nunca.","correct":"B","imageHash":"bdoe6v83.jpg","imageName":"bdoe6v83.jpg","topicName":"Sinalização luminosa, marcas no pavimento e outra sinalização"},{"question":"53) Os peões que se encontram do meu lado direito circulam correctamente naquele local?","optionA":"Sim.","optionB":"Não, os peões nunca podem utilizar uma pista especial.","optionC":"Não, porque é proibido correr nas pistas.","correct":"A","imageHash":"2pm9w6de.jpg","imageName":"2pm9w6de.jpg","topicName":"Circulação, segurança e veículos em missão urgente de socorro"},{"question":"54) Qual deve ser o último veículo a avançar, nesta situação?","optionA":"O meu veículo.","optionB":"O veículo cinzento.","optionC":"O motociclo.","correct":"B","imageHash":"qp39xzp4.jpg","imageName":"qp39xzp4.jpg","topicName":"Cedência de passagem"},{"question":"55) Qual a indicação dada pelo sinal de perigo?","optionA":"Queda de pedras.","optionB":"Bermas baixas.","optionC":"Obstrução de via.","correct":"B","imageHash":"386bvmpk.jpg","imageName":"386bvmpk.jpg","topicName":"Sinais de perigo"},{"question":"56) Este sinal adverte-me para o perigo de:","optionA":"Descida perigosa.","optionB":"Pavimento irregular.","optionC":"Pavimento escorregadio.","correct":"C","imageHash":"q8965j84.jpg","imageName":"q8965j84.jpg","topicName":"Sinais de perigo"},{"question":"57) Nos capacetes integrais (fechados","optionA":"Evitar o embaciamento da viseira.","optionB":"Anular os ruídos do ambiente rodoviário.","optionC":"Permitir a audição dos ruídos do ambiente rodoviário.","correct":"A","imageHash":"o8x3gr8g.jpg","imageName":"o8x3gr8g.jpg","topicName":"Equipamento de Protecção"},{"question":"58) Após o sinal, o estacionamento é:","optionA":"Limitado.","optionB":"Autorizado.","optionC":"Proibido.","correct":"B","imageHash":"vd7736dg.jpg","imageName":"vd7736dg.jpg","topicName":"Sinais de indicação"},{"question":"59) O sinal vertical que se encontra nesta via pública indica-me:","optionA":"Que estou obrigado a transitar com as luzes de cruzamento acesas.","optionB":"Que já não estou obrigado a transitar com as luzes de cruzamento acesas.","optionC":"Que devo utilizar os máximos apenas no cruzamento com outros veículos.","correct":"B","imageHash":"a8v5yxdk.jpg","imageName":"a8v5yxdk.jpg","topicName":"Estado físico do condutor, alcool, drogas e medicamentos, sinais de obrigação"},{"question":"60) Devo saber que este sinal vertical indica:","optionA":"Via reservada a veículos agrícolas.","optionB":"Trânsito proibido a veículos agrícolas.","optionC":"Saída de veículos agrícolas.","correct":"B","imageHash":"ydeoy9pz.jpg","imageName":"ydeoy9pz.jpg","topicName":"Sinais de proibição"},{"question":"61) As entidades fiscalizadoras do trânsito devem apreender o documento de identificação do veículo por circular:","optionA":"Sem oferecer condições de segurança.","optionB":"Sem luzes de estrada.","optionC":"Sem pneumático de reserva.","correct":"A","imageHash":"5dw7rz8g.jpg","imageName":"5dw7rz8g.jpg","topicName":"Títulos de condução, obtenção, revalidação, responsabilidade civil e criminal, contra-ordenações, cassação"},{"question":"62) Regra geral, o aumento da sinistralidade rodoviária é motivado:","optionA":"Sempre pela velocidade.","optionB":"Pela atitude e comportamento de alguns condutores.","optionC":"Sempre pelo comportamento dos peões.","correct":"B","imageHash":"bdoyavp3.jpg","imageName":"bdoyavp3.jpg","topicName":"Iluminação, passageiros e carga, condução defensiva e peões"},{"question":"63) Este veículo mostra sinais evidentes de abandono. Pode ser removido?","optionA":"Não, apenas o seu proprietário o pode fazer.","optionB":"Sim, se se mantiver neste local por tempo superior a 48 horas.","optionC":"Sim, se estiver estacionado neste local há pelo menos 24 horas.","correct":"B","imageHash":"vd77lrdg.jpg","imageName":"vd77lrdg.jpg","topicName":"Paragem, estacionamento e cruzamento de veículos"},{"question":"64) É-me permitido realizar a manobra de marcha atrás, neste local?","optionA":"Sim, porque não circulam veículos em sentido contrário.","optionB":"Sim, porque o local não é de visibilidade reduzida.","optionC":"Sim, se percorrer só dois metros.","correct":"B","imageHash":"qpyvxwpg.jpg","imageName":"qpyvxwpg.jpg","topicName":"Outras manobras"},{"question":"65) O álcool influencia, de forma negativa, o desempenho da tarefa da condução?","optionA":"Sim, mas apenas quando a taxa de álcool no sangue é muito elevada.","optionB":"Não, porque o álcool é um estimulante para a condução.","optionC":"Sim, sempre.","correct":"C","imageHash":"38657vpk.jpg","imageName":"38657vpk.jpg","topicName":"Estado físico do condutor, alcool, drogas e medicamentos, sinais de obrigação"},{"question":"66) Por norma, os motociclos de tipo desportivo/estrada equipados com amortecedor hidro-mecânico da direcção apresentam, quanto à sua afinação/regulação:","optionA":"Firmeza e estabilidade a alta velocidade desaparecendo o efeito a baixa velocidade.","optionB":"Firmeza e estabilidade a alta velocidade tornando-se muito firme em baixa.","optionC":"Suavidade de funcionamento, agindo contrariamente ao movimento que o condutor tentar impor.","correct":"B","imageHash":"6d5am98v.jpg","imageName":"6d5am98v.jpg","topicName":"Constituintes do veículo"},{"question":"67) O sinal vertical que se encontra nesta via pública indica-me que:","optionA":"Devo ceder a passagem ao veículo que transita em sentido contrário.","optionB":"A via pública tem dois sentidos de trânsito.","optionC":"Tenho prioridade de passagem.","correct":"A","imageHash":"386wn5pk.jpg","imageName":"386wn5pk.jpg","topicName":"Sinais de prescrição específica, sinais de cedência de passagem"},{"question":"68) Regra geral, um quadro de um motociclo é constituído por:","optionA":"Uma estrutura em aço, sempre aparafusada.","optionB":"Uma estrutura tubular maciça.","optionC":"Uma estrutura tubular de alta resistência.","correct":"C","imageHash":"j8lgkkd7.jpg","imageName":"j8lgkkd7.jpg","topicName":"Constituintes do veículo"},{"question":"69) Na situação da figura, em que conduzo um motociclo sem ABS, se necessitar de travar, devo:","optionA":"Utilizar só o travão da frente.","optionB":"Utilizar apenas o travão de trás.","optionC":"Utilizar os dois travões, exercendo uma maior pressão sobre o da frente.","correct":"C","imageHash":"j8ggww8w.jpg","imageName":"j8ggww8w.jpg","topicName":"Visibilidade relativamente aos outros utentes da via"},{"question":"70) Como se designa a via de trânsito à minha direita e que permite a entrada na auto-estrada?","optionA":"Via reversível.","optionB":"Via de abrandamento.","optionC":"Via de aceleração.","correct":"C","imageHash":"bdogevp3.jpg","imageName":"bdogevp3.jpg","topicName":"Vias de trânsito, condições ambientais adversas"},{"question":"71) Este sinal indica a aproximação de:","optionA":"Um cruzamento com via sem prioridade.","optionB":"Um entroncamento com via sem prioridade.","correct":"B","imageHash":"6d5lv4pv.jpg","imageName":"6d5lv4pv.jpg","topicName":"Sinais de prescrição específica, sinais de cedência de passagem"},{"question":"72) O condutor deve ter uma atenção especial ao comportamento do peão idoso?","optionA":"Não.","optionB":"Sim.","correct":"B","imageHash":"adqnb2dj.jpg","imageName":"adqnb2dj.jpg","topicName":"Iluminação, passageiros e carga, condução defensiva e peões"},{"question":"73) Nas auto-estradas podem ser estabelecidos limites de velocidade inferiores aos determinados na lei.","optionA":"A afirmação é verdadeira.","optionB":"A afirmação é falsa.","correct":"A","imageHash":"j8lkxlp7.jpg","imageName":"j8lkxlp7.jpg","topicName":"Velocidade"},{"question":"74) Quando a faixa de rodagem for demasiado estreita, deve ceder a passagem quem chegar primeiro ao troço da via de trânsito. Concorda com esta afirmação?","optionA":"Sim.","optionB":"Não.","correct":"B","imageHash":"bdob7v83.jpg","imageName":"bdob7v83.jpg","topicName":"Cedência de passagem"},{"question":"75) Circulo a 60 Km/h. Transito em excesso de velocidade?","optionA":"Sim.","optionB":"Não.","correct":"A","imageHash":"xpjaynpl.jpg","imageName":"xpjaynpl.jpg","topicName":"Velocidade"},{"question":"76) O sinal vertical indica que no troço de via onde o mesmo se aplica, o trânsito se faz simultaneamente nos dois sentidos.","optionA":"Certo.","optionB":"Errado.","correct":"B","imageHash":"5dwvjo8g.jpg","imageName":"5dwvjo8g.jpg","topicName":"Sinais de prescrição específica, sinais de cedência de passagem"},{"question":"77) O cumprimento das regras e sinais de trânsito é um contributo para a segurança rodoviária.","optionA":"Certo.","optionB":"Errado.","correct":"A","imageHash":"kpb9ra89.jpg","imageName":"kpb9ra89.jpg","topicName":"Iluminação, passageiros e carga, condução defensiva e peões"},{"question":"78) O condutor de um triciclo sem caixa rígida está obrigado a utilizar capacete de protecção?","optionA":"Sim.","optionB":"Não.","correct":"A","imageHash":"2pmyazpe.jpg","imageName":"2pmyazpe.jpg","topicName":"Equipamento de Protecção"},{"question":"79) O condutor de um motociclo deve saber que ao circular com o piso molhado ou escorregadio a distância de travagem diminui. Concorda com a afirmação?","optionA":"Sim.","optionB":"Não.","correct":"B","imageHash":"ap2e6op2.jpg","imageName":"ap2e6op2.jpg","topicName":"Classificação das vias"},{"question":"80) Numa localidade a velocidade máxima legalmente permitida é:","optionA":"60 Km/h.","optionB":"50 Km/h.","optionC":"40 Km/h.","correct":"B","imageHash":"kparobdg.jpg","imageName":"kparobdg.jpg","topicName":"Velocidade"},{"question":"81) Um dos efeitos da fadiga na condução é:","optionA":"O aumento do tempo de reacção.","optionB":"O aumento da capacidade de atenção.","optionC":"A redução do tempo de reacção.","correct":"A","imageHash":"z8zo7ldn.jpg","imageName":"z8zo7ldn.jpg","topicName":"Estado físico do condutor, alcool, drogas e medicamentos, sinais de obrigação"},{"question":"82) Em que momento deve avançar o veículo de tracção animal.","optionA":"Em primeiro lugar.","optionB":"Em último lugar.","optionC":"Antes do meu veículo e após o motociclo.","correct":"B","imageHash":"j8gwx3dw.jpg","imageName":"j8gwx3dw.jpg","topicName":"Cedência de passagem"},{"question":"83) Nesta situação, devo estar especialmente atento:","optionA":"Ao tipo de pavimento em que circulo.","optionB":"Ao comportamento dos peões.","optionC":"Ao limite máximo de velocidade imposto para a circulação nas localidades.","correct":"B","imageHash":"386g45dk.jpg","imageName":"386g45dk.jpg","topicName":"Iluminação, passageiros e carga, condução defensiva e peões"},{"question":"84) O sinal proíbe o trânsito:","optionA":"A veículos de duas rodas.","optionB":"A todos os ciclomotores.","optionC":"Apenas a motociclos.","correct":"A","imageHash":"6d5gx98v.jpg","imageName":"6d5gx98v.jpg","topicName":"Sinais de proibição"},{"question":"85) Nesta situação devo transitar com velocidade especialmente moderada, devido:","optionA":"Às condições de visibilidade e à existência de uma linha contínua.","optionB":"Às condições de aderência e à existência de uma linha contínua.","optionC":"Às condições de aderência e visibilidade.","correct":"C","imageHash":"r84gjb8o.jpg","imageName":"r84gjb8o.jpg","topicName":"Vias de trânsito, condições ambientais adversas"},{"question":"86) O motociclista vai mudar de via de trânsito, num local muito congestionado \u0027uma olhadela\u0027 por cima do ombro pode ajudá-lo, porque:","optionA":"Os espelhos podem não apanhar o ângulo morto.","optionB":"Deste modo evita assinalar a sua presença.","optionC":"Assim os outros condutores cedem-lhe a passagem.","correct":"A","imageHash":"qpy5e38g.jpg","imageName":"qpy5e38g.jpg","topicName":"Visibilidade relativamente aos outros utentes da via"},{"question":"87) A condução sob a influência do álcool:","optionA":"Diminui o tempo de recuperação após encandeamento.","optionB":"Não altera o tempo de recuperação após encandeamento.","optionC":"Aumenta o tempo de recuperação após encandeamento.","correct":"C","imageHash":"z8z7bnpn.jpg","imageName":"z8z7bnpn.jpg","topicName":"Estado físico do condutor, alcool, drogas e medicamentos, sinais de obrigação"},{"question":"88) Pretendo mudar de direcção à direita. Devo:","optionA":"Parar.","optionB":"Avançar com precaução.","optionC":"Avançar rapidamente.","correct":"B","imageHash":"j8gnywdw.jpg","imageName":"j8gnywdw.jpg","topicName":"Sinalização luminosa, marcas no pavimento e outra sinalização"},{"question":"89) O sinal indica a aproximação de:","optionA":"Escola de equitação.","optionB":"Hipódromo.","optionC":"Cavaleiros.","correct":"C","imageHash":"5pnn5npe.jpg","imageName":"5pnn5npe.jpg","topicName":"Sinais de perigo"},{"question":"90) O que devo fazer nesta situação?","optionA":"Parar e ceder a passagem.","optionB":"Parar e ceder a passagem, porque o outro veículo tem motor.","optionC":"Ceder a passagem, porque o outro condutor segue em frente.","correct":"A","imageHash":"j8ln7bp7.jpg","imageName":"j8ln7bp7.jpg","topicName":"Cedência de passagem"},{"question":"91) Este sinal vertical indica-me o local exacto de uma passagem de nível:","optionA":"Com guarda com duas ou mais vias.","optionB":"Sem guarda com duas ou mais vias.","optionC":"Com guarda com uma via.","correct":"B","imageHash":"qpy55r8g.jpg","imageName":"qpy55r8g.jpg","topicName":"Classificação das vias"},{"question":"92) O nível de óleo do motor de um motociclo deve ser verificado:","optionA":"Com o motociclo na vertical, imobilizado e com o motor ligado.","optionB":"Com o motociclo no descanso lateral e num plano oblíquo.","optionC":"Com o motociclo no descanso central e com o motor parado.","correct":"C","imageHash":"bdoaa2p3.jpg","imageName":"bdoaa2p3.jpg","topicName":"Constituintes do veículo"},{"question":"93) Na condução de um veículo, a distância de travagem varia:","optionA":"Com a rotação do motor.","optionB":"Com a velocidade do veículo.","optionC":"Com o tempo de reacção do condutor.","correct":"B","imageHash":"a8v4498k.jpg","imageName":"a8v4498k.jpg","topicName":"Visibilidade relativamente aos outros utentes da via"},{"question":"94) O sinal indica-me a existência:","optionA":"De uma ponte móvel.","optionB":"De um teleférico a seguir à ponte.","optionC":"De um cais ou precipício a seguir à ponte.","correct":"A","imageHash":"kpblma89.jpg","imageName":"kpblma89.jpg","topicName":"Sinais de indicação"},{"question":"95) A pressão dos pneumáticos dos motociclos:","optionA":"É sempre maior no pneumático de trás.","optionB":"É sempre igual nos dois pneumáticos.","optionC":"Depende do tipo de pneumáticos que equipam o veículo.","correct":"C","imageHash":"j8gng3dw.jpg","imageName":"j8gng3dw.jpg","topicName":"Constituintes do veículo"},{"question":"96) Se pretender mudar de direcção à esquerda, devo:","optionA":"Aproximar o veículo da marca rodoviária que divide as duas vias.","optionB":"Ocupar a via de trânsito adequada.","optionC":"Desistir da manobra porque o sinal está vermelho.","correct":"B","imageHash":"ap2nllp2.jpg","imageName":"ap2nllp2.jpg","topicName":"Outras manobras"},{"question":"97) Perante a sinalização, que encontro neste local, devo:","optionA":"Diminuir a distância de segurança.","optionB":"Moderar a velocidade.","optionC":"Diminuir a distância de paragem.","correct":"B","imageHash":"z8k3n4d5.jpg","imageName":"z8k3n4d5.jpg","topicName":"Vias de trânsito, condições ambientais adversas"},{"question":"98) A responsabilidade pela correcta utilização dos equipamentos de retenção para menores é:","optionA":"Do condutor.","optionB":"Dos pais.","optionC":"Dos tutores.","correct":"A","imageHash":"5dwy9l8g.jpg","imageName":"5dwy9l8g.jpg","topicName":"Títulos de condução, obtenção, revalidação, responsabilidade civil e criminal, contra-ordenações, cassação"},{"question":"99) Perante o sinal de informação fico a saber que:","optionA":"Só é permitido o estacionamento de autocarros.","optionB":"É permitido o estacionamento a todos os veículos.","optionC":"É permitida a paragem, mas não o estacionamento de automóveis.","correct":"B","imageHash":"qpyb238g.jpg","imageName":"qpyb238g.jpg","topicName":"Ultrapassagem"},{"question":"100) Perante este sinal fico a saber que:","optionA":"Terminou a proibição do uso de sinais sonoros.","optionB":"É proibido o uso de sinais sonoros.","optionC":"É proibido ultrapassar sem buzinar.","correct":"A","imageHash":"2pmrq2de.jpg","imageName":"2pmrq2de.jpg","topicName":"Sinais de proibição"}]}
